{"path": "/Users/lfoppiano/development/projects/grobid/grobid-superconductors/resources/dataset/superconductors/corpus/pdf/batches/batch-3/P063224522-CC.pdf", "categories": [{"term": "starting composition", "score": "0.05934795027448197"}, {"term": "phase diagram", "score": "0.022515064930539803"}, {"term": "lattice constants", "score": "0.021235730913025122"}, {"term": "lattice parameters", "score": "0.019471835050586483"}, {"term": "line compound", "score": "0.015987472656961182"}, {"term": "top surface", "score": "0.015341445797431776"}, {"term": "composition", "score": "0.014895206981173503"}, {"term": "isotropic strain", "score": "0.011758717864762187"}, {"term": "peak broadening", "score": "0.010417791368266758"}, {"term": "thermal expansion", "score": "0.009631888384439626"}, {"term": "stoichiometry", "score": "0.008909742252291125"}]}